enumpaths/__init__.py
enumpaths/main.py
enumpaths-1.0.dist-info/METADATA
enumpaths-1.0.dist-info/WHEEL
enumpaths-1.0.dist-info/entry_points.txt
enumpaths-1.0.dist-info/top_level.txt
enumpaths-1.0.dist-info/RECORD
