Metadata-Version: 2.1
Name: enumpaths
Version: 1.0
Summary: simple Python tool iterates through URLs sending a proxied GET request (for Burp).
Home-page: https://github.com/0xBruno/enumpaths
Author: 0xBruno
Author-email: 0xbruno90@gmail.com
License: UNKNOWN
Platform: UNKNOWN
Requires-Python: >=3.6
Requires-Dist: click (==7.1.2)
Requires-Dist: requests (==2.25.0)
